{
  "appPageId" : "bb216c92-be6b-4078-8ead-47c6f09c8cad",
  "componentName" : "siteforce:sldsOneColLayout",
  "dataProviders" : [ ],
  "id" : "0c14d5e8-563d-46af-a187-604809e1c235",
  "label" : "Forgot Password",
  "regions" : [ {
    "components" : [ {
      "componentAttributes" : {
        "richTextValue" : "<div style=\"text-align: center;\"><span class=\"inverseTextColor\" style=\"font-size:22px\">PASSWORD RESET</span></div>"
      },
      "componentName" : "forceCommunity:richTextInline",
      "id" : "a6ed8bee-9e47-40cc-861f-aac24aacdc99",
      "renderPriority" : "NEUTRAL",
      "renditionMap" : { },
      "type" : "component"
    }, {
      "componentAttributes" : {
        "richTextValue" : "<div class=\"inverseTextColor\" style=\"text-align: center;\">To reset your password, we'll need your username.<br/> We'll send password reset instructions to the email address associated with your account.</div>"
      },
      "componentName" : "forceCommunity:richTextInline",
      "id" : "8a843d28-b81a-411b-968c-8d4a0e0b8cb6",
      "renderPriority" : "NEUTRAL",
      "renditionMap" : { },
      "type" : "component"
    }, {
      "componentAttributes" : {
        "checkEmailUrl" : "./CheckPasswordResetEmail",
        "submitButtonLabel" : "Reset Password",
        "usernameLabel" : "Username"
      },
      "componentName" : "salesforceIdentity:forgotPassword2",
      "id" : "f67ad6b1-ddc4-4b2c-869a-e0ea77d26775",
      "renderPriority" : "NEUTRAL",
      "renditionMap" : { },
      "type" : "component"
    }, {
      "componentAttributes" : {
        "richTextValue" : "<div style=\"text-align: center;\"><a class=\"inverseTextColor\" href=\"./\">Cancel</a></div>"
      },
      "componentName" : "forceCommunity:richTextInline",
      "id" : "55271ead-f516-45f8-9653-46dc5ac426a9",
      "renderPriority" : "NEUTRAL",
      "renditionMap" : { },
      "type" : "component"
    } ],
    "id" : "5bbb73f7-e5f6-4daa-ba94-6a367d484c03",
    "regionName" : "content",
    "type" : "region"
  }, {
    "components" : [ {
      "componentAttributes" : {
        "customHeadTags" : "",
        "description" : "",
        "title" : "Forgot Password"
      },
      "componentName" : "forceCommunity:seoAssistant",
      "id" : "961c385c-dd94-48f6-bee4-5ff4975812ee",
      "renditionMap" : { },
      "type" : "component"
    } ],
    "id" : "33bdab26-2ab6-4b9e-b549-7247f25e692b",
    "regionName" : "sfdcHiddenRegion",
    "type" : "region"
  } ],
  "themeLayoutType" : "Login",
  "type" : "view",
  "viewType" : "forgot-password"
}